opensignalsreader/__init__.py
opensignalsreader/__version__.py
opensignalsreader/opensignalsreader.py
opensignalsreader/files/SampleECG.txt
opensignalsreader/transfer_functions/__init__.py
opensignalsreader/transfer_functions/bio.py
opensignalsreader/transfer_functions/bit.py
opensignalsreader-0.2.2.dist-info/LICENSE.txt
opensignalsreader-0.2.2.dist-info/METADATA
opensignalsreader-0.2.2.dist-info/WHEEL
opensignalsreader-0.2.2.dist-info/top_level.txt
opensignalsreader-0.2.2.dist-info/RECORD
