Metadata-Version: 2.1
Name: opensignalsreader
Version: 0.2.2
Summary: Python package to read OpenSignals (r)evolution files.
Home-page: https://github.com/PGomes92/opensignalsreader
Author: Pedro Gomes
Author-email: pgomes92@gmail.com
License: UNKNOWN
Keywords: opensignals,opensignalsreader,physiological signals,BITalino,biosignalsplux
Platform: UNKNOWN
Classifier: Intended Audience :: Developers
Classifier: Intended Audience :: Education
Classifier: Intended Audience :: Science/Research
Classifier: Natural Language :: English
Classifier: License :: OSI Approved :: BSD License
Classifier: Programming Language :: Python
Classifier: Programming Language :: Python :: 2.7
Classifier: Programming Language :: Python :: 3
Classifier: Operating System :: OS Independent
Requires-Dist: numpy
Requires-Dist: matplotlib
